pycones/__init__.py
pycones-0.1.10.dist-info/METADATA
pycones-0.1.10.dist-info/WHEEL
pycones-0.1.10.dist-info/RECORD
