Metadata-Version: 2.1
Name: pycones
Version: 0.1.10
Summary: 
Author: william
Author-email: william_swl@163.com
Requires-Python: >=3.6
Classifier: Programming Language :: Python :: 3
Classifier: Programming Language :: Python :: 3.6
Classifier: Programming Language :: Python :: 3.7
Classifier: Programming Language :: Python :: 3.8
Classifier: Programming Language :: Python :: 3.9
Classifier: Programming Language :: Python :: 3.10
Classifier: Programming Language :: Python :: 3.11
Requires-Dist: matplotlib (>=3.0)
Requires-Dist: numpy (>=1.0)
Requires-Dist: pandas (>=2.0)
